hollowfoot/__init__.py
hollowfoot/_version.py
hollowfoot/analysis.py
hollowfoot/operation.py
hollowfoot/py.typed
hollowfoot/readers.py
hollowfoot/xafs_analysis.py
hollowfoot-0.2.0.dist-info/METADATA
hollowfoot-0.2.0.dist-info/WHEEL
hollowfoot-0.2.0.dist-info/licenses/AUTHORS.rst
hollowfoot-0.2.0.dist-info/licenses/LICENSE
hollowfoot-0.2.0.dist-info/RECORD
