Metadata-Version: 2.4
Name: hollowfoot
Version: 0.2.0
Summary: Companion workflow engine for xraylarch.
Project-URL: Homepage, https://github.com/spc-group/hollowfoot
Author-email: Mark Wolfman <wolfman@anl.gov>
License-File: AUTHORS.rst
License-File: LICENSE
Classifier: Development Status :: 3 - Alpha
Classifier: Operating System :: OS Independent
Classifier: Programming Language :: Python :: 3
Classifier: Topic :: Scientific/Engineering
Requires-Python: >=3.7
Requires-Dist: numpy
Requires-Dist: xraylarch
